[
  { "id": "STK685617", "publisher": "MARVEL COMICS", "title": "1602 WITCH HUNTER ANGELA #4", "price": 3.99, "imagePath": "http://s3.amazonaws.com/southsidecomics/items/STK/685/617/STK685617_200.jpg" },
  { "id": "STK685618", "publisher": "MARVEL COMICS", "title": "1872 #4", "price": 3.99, "imagePath": "http://s3.amazonaws.com/southsidecomics/items/STK/685/618/STK685618_200.jpg" },
  { "id": "STK685598", "publisher": "MARVEL COMICS", "title": "AGE OF APOCALYPSE #5", "price": 3.99, "imagePath": "http://s3.amazonaws.com/southsidecomics/items/STK/685/598/STK685598_200.jpg" },
  { "id": "STK685856", "publisher": "MARVEL COMICS", "title": "AMAZING SPIDER-MAN #1", "price": 5.99, "imagePath": "http://s3.amazonaws.com/southsidecomics/items/STK/685/856/STK685856_200.jpg" },
  { "id": "STK685857", "publisher": "MARVEL COMICS", "title": "ASTONISHING ANT-MAN #1", "price": 3.99, "imagePath": "http://s3.amazonaws.com/southsidecomics/items/STK/685/857/STK685857_200.jpg" },
  { "id": "STK685599", "publisher": "MARVEL COMICS", "title": "CAPTAIN AMERICA WHITE #3", "price": 3.99, "imagePath": "http://s3.amazonaws.com/southsidecomics/items/STK/685/599/STK685599_200.jpg" }
]